jupyter_archive/__init__.py
jupyter_archive/_version.py
jupyter_archive/handlers.py
jupyter_archive/tests/test_archive_handler.py
jupyter_archive-3.4.0.data/data/etc/jupyter/jupyter_server_config.d/jupyter-archive.json
jupyter_archive-3.4.0.data/data/share/jupyter/labextensions/@hadim/jupyter-archive/package.json
jupyter_archive-3.4.0.data/data/share/jupyter/labextensions/@hadim/jupyter-archive/schemas/@hadim/jupyter-archive/archive.json
jupyter_archive-3.4.0.data/data/share/jupyter/labextensions/@hadim/jupyter-archive/schemas/@hadim/jupyter-archive/package.json.orig
jupyter_archive-3.4.0.data/data/share/jupyter/labextensions/@hadim/jupyter-archive/static/747.e392128c48fafc062daa.js
jupyter_archive-3.4.0.data/data/share/jupyter/labextensions/@hadim/jupyter-archive/static/933.181cd7cb954c15b4d43e.js
jupyter_archive-3.4.0.data/data/share/jupyter/labextensions/@hadim/jupyter-archive/static/remoteEntry.c3551e86769ef3973316.js
jupyter_archive-3.4.0.data/data/share/jupyter/labextensions/@hadim/jupyter-archive/static/style.js
jupyter_archive-3.4.0.data/data/share/jupyter/labextensions/@hadim/jupyter-archive/static/third-party-licenses.json
jupyter_archive-3.4.0.data/data/share/jupyter/labextensions/@hadim/jupyter-archive/install.json
jupyter_archive-3.4.0.dist-info/METADATA
jupyter_archive-3.4.0.dist-info/WHEEL
jupyter_archive-3.4.0.dist-info/licenses/LICENSE
jupyter_archive-3.4.0.dist-info/RECORD
