Metadata-Version: 2.1
Name: jupyter-archive
Version: 3.4.0
Summary: A JupyterLab extension to make, download and extract archive files.
Project-URL: Homepage, https://github.com/jupyterlab-contrib/jupyter-archive
Project-URL: Bug Tracker, https://github.com/jupyterlab-contrib/jupyter-archive/issues
Project-URL: Repository, https://github.com/jupyterlab-contrib/jupyter-archive.git
Author-email: Hadrien Mary <hadrien.mary@gmail.com>
License: Copyright (c) 2011-2020, Hadrien Mary, Frederic Collonval
License-File: LICENSE
Classifier: Framework :: Jupyter
Classifier: Framework :: Jupyter :: JupyterLab
Classifier: Framework :: Jupyter :: JupyterLab :: 3
Classifier: Framework :: Jupyter :: JupyterLab :: 4
Classifier: Framework :: Jupyter :: JupyterLab :: Extensions
Classifier: Framework :: Jupyter :: JupyterLab :: Extensions :: Prebuilt
Classifier: License :: OSI Approved :: BSD License
Classifier: Programming Language :: Python
Classifier: Programming Language :: Python :: 3
Classifier: Programming Language :: Python :: 3.6
Classifier: Programming Language :: Python :: 3.7
Classifier: Programming Language :: Python :: 3.8
Classifier: Programming Language :: Python :: 3.9
Classifier: Programming Language :: Python :: 3.10
Classifier: Programming Language :: Python :: 3.11
Requires-Python: >=3.6
Requires-Dist: jupyter-server<3,>=1.21
Provides-Extra: test
Requires-Dist: coverage; extra == 'test'
Requires-Dist: pytest; extra == 'test'
Requires-Dist: pytest-asyncio; extra == 'test'
Requires-Dist: pytest-cov; extra == 'test'
Requires-Dist: pytest-jupyter[server]>=0.6.0; extra == 'test'
